<?xml version="1.0" encoding="UTF-8"?>

<!-- generated on 2026-05-19T17:09:24.745540+01:00 by Eclipse SUMO sumo 1.26.0
<sumoConfiguration xmlns:xsi="http://www.w3.org/2001/XMLSchema-instance" xsi:noNamespaceSchemaLocation="http://sumo.dlr.de/xsd/sumoConfiguration.xsd">

    <input>
        <net-file value="/home/miguel/6.Projects/BayesianFinalProject/sumo/networks/1st.net.xml"/>
        <route-files value="/home/miguel/6.Projects/BayesianFinalProject/sumo/routes/routes.rou.xml"/>
    </input>

    <output>
        <tripinfo-output value="/home/miguel/6.Projects/BayesianFinalProject/data/raw/trips_info.xml"/>
    </output>

</sumoConfiguration>
-->

<tripinfos xmlns:xsi="http://www.w3.org/2001/XMLSchema-instance" xsi:noNamespaceSchemaLocation="http://sumo.dlr.de/xsd/tripinfo_file.xsd">
    <tripinfo id="0" depart="0.00" departLane="E1_2_EB_0" departPos="5.10" departSpeed="0.00" departDelay="0.00" arrival="32.00" arrivalLane="E4_5_EB_0" arrivalPos="93.69" arrivalSpeed="14.38" duration="32.00" routeLength="394.90" waitingTime="0.00" waitingCount="0" stopTime="0.00" timeLoss="4.71" rerouteNo="1" devices="tripinfo_0 routing_0" vType="DEFAULT_VEHTYPE" speedFactor="1.06" vaporized=""/>
    <tripinfo id="3" depart="11.00" departLane="E4_7_SEB_0" departPos="5.10" departSpeed="0.00" departDelay="0.60" arrival="45.00" arrivalLane="E4_5_EB_0" arrivalPos="93.69" arrivalSpeed="14.07" duration="34.00" routeLength="402.12" waitingTime="0.00" waitingCount="0" stopTime="0.00" timeLoss="6.83" rerouteNo="0" devices="tripinfo_3 routing_3" vType="DEFAULT_VEHTYPE" speedFactor="1.08" vaporized=""/>
    <tripinfo id="9" depart="32.00" departLane="E3_6_NWB_0" departPos="5.10" departSpeed="0.00" departDelay="0.80" arrival="67.00" arrivalLane="E6_7_NEB_0" arrivalPos="125.94" arrivalSpeed="11.26" duration="35.00" routeLength="337.15" waitingTime="0.00" waitingCount="0" stopTime="0.00" timeLoss="5.53" rerouteNo="0" devices="tripinfo_9 routing_9" vType="DEFAULT_VEHTYPE" speedFactor="0.86" vaporized=""/>
    <tripinfo id="13" depart="46.00" departLane="E1_2_EB_0" departPos="5.10" departSpeed="0.00" departDelay="0.93" arrival="77.00" arrivalLane="E4_5_EB_0" arrivalPos="93.69" arrivalSpeed="15.57" duration="31.00" routeLength="394.90" waitingTime="0.00" waitingCount="0" stopTime="0.00" timeLoss="5.00" rerouteNo="1" devices="tripinfo_13 routing_13" vType="DEFAULT_VEHTYPE" speedFactor="1.12" vaporized=""/>
    <tripinfo id="12" depart="42.00" departLane="E6_7_SWB_0" departPos="5.10" departSpeed="0.00" departDelay="0.40" arrival="79.00" arrivalLane="E2_3_EB_0" arrivalPos="83.62" arrivalSpeed="14.20" duration="37.00" routeLength="417.80" waitingTime="0.00" waitingCount="0" stopTime="0.00" timeLoss="6.70" rerouteNo="1" devices="tripinfo_12 routing_12" vType="DEFAULT_VEHTYPE" speedFactor="1.05" vaporized=""/>
    <tripinfo id="6" depart="21.00" departLane="E3_6_NWB_0" departPos="5.10" departSpeed="0.00" departDelay="0.20" arrival="85.00" arrivalLane="E3_4_WB_0" arrivalPos="85.58" arrivalSpeed="13.85" duration="64.00" routeLength="739.62" waitingTime="0.00" waitingCount="0" stopTime="0.00" timeLoss="11.02" rerouteNo="1" devices="tripinfo_6 routing_6" vType="DEFAULT_VEHTYPE" speedFactor="1.05" vaporized=""/>
    <tripinfo id="2" depart="7.00" departLane="E3_4_WB_0" departPos="5.10" departSpeed="0.00" departDelay="0.07" arrival="86.00" arrivalLane="E3_4_EB_0" arrivalPos="85.58" arrivalSpeed="13.52" duration="79.00" routeLength="672.90" waitingTime="7.00" waitingCount="2" stopTime="0.00" timeLoss="28.27" rerouteNo="1" devices="tripinfo_2 routing_2" vType="DEFAULT_VEHTYPE" speedFactor="1.01" vaporized=""/>
    <tripinfo id="5" depart="18.00" departLane="E4_5_WB_0" departPos="5.10" departSpeed="0.00" departDelay="0.67" arrival="90.00" arrivalLane="E3_6_SEB_0" arrivalPos="196.67" arrivalSpeed="10.64" duration="72.00" routeLength="680.31" waitingTime="0.00" waitingCount="0" stopTime="0.00" timeLoss="10.18" rerouteNo="1" devices="tripinfo_5 routing_5" vType="DEFAULT_VEHTYPE" speedFactor="0.83" vaporized=""/>
    <tripinfo id="17" depart="59.00" departLane="E4_5_WB_0" departPos="5.10" departSpeed="0.00" departDelay="0.07" arrival="95.00" arrivalLane="E4_7_NWB_0" arrivalPos="298.61" arrivalSpeed="12.59" duration="36.00" routeLength="398.10" waitingTime="0.00" waitingCount="0" stopTime="0.00" timeLoss="4.81" rerouteNo="0" devices="tripinfo_17 routing_17" vType="DEFAULT_VEHTYPE" speedFactor="0.94" vaporized=""/>
    <tripinfo id="7" depart="25.00" departLane="E4_5_WB_0" departPos="5.10" departSpeed="0.00" departDelay="0.73" arrival="103.00" arrivalLane="E6_7_SWB_0" arrivalPos="125.94" arrivalSpeed="4.11" duration="78.00" routeLength="540.44" waitingTime="21.00" waitingCount="1" stopTime="0.00" timeLoss="32.29" rerouteNo="1" devices="tripinfo_7 routing_7" vType="DEFAULT_VEHTYPE" speedFactor="0.89" vaporized=""/>
    <tripinfo id="23" depart="85.00" departLane="E2_6_NB_0" departPos="5.10" departSpeed="0.00" departDelay="5.27" arrival="103.00" arrivalLane="E2_6_NB_0" arrivalPos="175.06" arrivalSpeed="11.44" duration="18.00" routeLength="169.96" waitingTime="0.00" waitingCount="0" stopTime="0.00" timeLoss="3.74" rerouteNo="1" devices="tripinfo_23 routing_23" vType="DEFAULT_VEHTYPE" speedFactor="0.89" vaporized=""/>
    <tripinfo id="8" depart="28.00" departLane="E4_7_SEB_0" departPos="5.10" departSpeed="0.00" departDelay="0.27" arrival="112.00" arrivalLane="E3_6_SEB_0" arrivalPos="196.67" arrivalSpeed="11.86" duration="84.00" routeLength="879.58" waitingTime="0.00" waitingCount="0" stopTime="0.00" timeLoss="12.96" rerouteNo="1" devices="tripinfo_8 routing_8" vType="DEFAULT_VEHTYPE" speedFactor="0.94" vaporized=""/>
    <tripinfo id="21" depart="73.00" departLane="E2_6_SB_0" departPos="5.10" departSpeed="0.00" departDelay="0.20" arrival="113.00" arrivalLane="E3_4_EB_0" arrivalPos="85.58" arrivalSpeed="6.82" duration="40.00" routeLength="368.51" waitingTime="0.00" waitingCount="0" stopTime="0.00" timeLoss="12.87" rerouteNo="1" devices="tripinfo_21 routing_21" vType="DEFAULT_VEHTYPE" speedFactor="1.01" vaporized=""/>
    <tripinfo id="19" depart="66.00" departLane="E3_4_WB_0" departPos="5.10" departSpeed="0.00" departDelay="0.13" arrival="114.00" arrivalLane="E3_6_SEB_0" arrivalPos="196.67" arrivalSpeed="15.95" duration="48.00" routeLength="571.87" waitingTime="0.00" waitingCount="0" stopTime="0.00" timeLoss="10.53" rerouteNo="1" devices="tripinfo_19 routing_19" vType="DEFAULT_VEHTYPE" speedFactor="1.16" vaporized=""/>
    <tripinfo id="4" depart="14.00" departLane="E6_7_SWB_0" departPos="5.10" departSpeed="0.00" departDelay="0.13" arrival="115.00" arrivalLane="E4_7_SEB_0" arrivalPos="298.61" arrivalSpeed="8.30" duration="101.00" routeLength="1073.40" waitingTime="1.00" waitingCount="1" stopTime="0.00" timeLoss="23.22" rerouteNo="1" devices="tripinfo_4 routing_4" vType="DEFAULT_VEHTYPE" speedFactor="1.03" vaporized=""/>
    <tripinfo id="22" depart="82.00" departLane="E3_4_WB_0" departPos="5.10" departSpeed="0.00" departDelay="5.73" arrival="116.00" arrivalLane="E2_6_NB_0" arrivalPos="175.06" arrivalSpeed="12.66" duration="34.00" routeLength="363.35" waitingTime="0.00" waitingCount="0" stopTime="0.00" timeLoss="6.03" rerouteNo="1" devices="tripinfo_22 routing_22" vType="DEFAULT_VEHTYPE" speedFactor="0.97" vaporized=""/>
    <tripinfo id="15" depart="52.00" departLane="E2_6_NB_0" departPos="5.10" departSpeed="0.00" departDelay="0.00" arrival="122.00" arrivalLane="E3_4_WB_0" arrivalPos="85.58" arrivalSpeed="12.67" duration="70.00" routeLength="720.09" waitingTime="0.00" waitingCount="0" stopTime="0.00" timeLoss="12.87" rerouteNo="1" devices="tripinfo_15 routing_15" vType="DEFAULT_VEHTYPE" speedFactor="0.93" vaporized=""/>
    <tripinfo id="1" depart="4.00" departLane="E3_4_WB_0" departPos="5.10" departSpeed="0.00" departDelay="0.53" arrival="123.00" arrivalLane="E6_7_SWB_0" arrivalPos="125.94" arrivalSpeed="12.58" duration="119.00" routeLength="1129.44" waitingTime="6.00" waitingCount="1" stopTime="0.00" timeLoss="27.58" rerouteNo="1" devices="tripinfo_1 routing_1" vType="DEFAULT_VEHTYPE" speedFactor="0.94" vaporized=""/>
    <tripinfo id="31" depart="108.00" departLane="E3_4_WB_0" departPos="5.10" departSpeed="0.00" departDelay="0.53" arrival="124.00" arrivalLane="E2_3_WB_0" arrivalPos="83.62" arrivalSpeed="14.88" duration="16.00" routeLength="179.26" waitingTime="0.00" waitingCount="0" stopTime="0.00" timeLoss="4.37" rerouteNo="0" devices="tripinfo_31 routing_31" vType="DEFAULT_VEHTYPE" speedFactor="1.15" vaporized=""/>
    <tripinfo id="10" depart="35.00" departLane="E4_5_WB_0" departPos="5.10" departSpeed="0.00" departDelay="0.33" arrival="126.00" arrivalLane="E2_6_SB_0" arrivalPos="175.06" arrivalSpeed="14.46" duration="91.00" routeLength="587.85" waitingTime="39.00" waitingCount="1" stopTime="0.00" timeLoss="49.94" rerouteNo="1" devices="tripinfo_10 routing_10" vType="DEFAULT_VEHTYPE" speedFactor="1.09" vaporized=""/>
    <tripinfo id="11" depart="39.00" departLane="E3_4_WB_0" departPos="5.10" departSpeed="0.00" departDelay="0.87" arrival="127.00" arrivalLane="E4_5_EB_0" arrivalPos="93.69" arrivalSpeed="14.18" duration="88.00" routeLength="781.34" waitingTime="9.00" waitingCount="1" stopTime="0.00" timeLoss="30.62" rerouteNo="1" devices="tripinfo_11 routing_11" vType="DEFAULT_VEHTYPE" speedFactor="1.03" vaporized=""/>
    <tripinfo id="18" depart="63.00" departLane="E6_7_SWB_0" departPos="5.10" departSpeed="0.00" departDelay="0.60" arrival="131.00" arrivalLane="E3_4_EB_0" arrivalPos="85.58" arrivalSpeed="11.72" duration="68.00" routeLength="442.09" waitingTime="22.00" waitingCount="1" stopTime="0.00" timeLoss="32.41" rerouteNo="1" devices="tripinfo_18 routing_18" vType="DEFAULT_VEHTYPE" speedFactor="0.94" vaporized=""/>
    <tripinfo id="20" depart="70.00" departLane="E4_5_WB_0" departPos="5.10" departSpeed="0.00" departDelay="0.67" arrival="147.00" arrivalLane="E3_4_EB_0" arrivalPos="85.58" arrivalSpeed="13.72" duration="77.00" routeLength="781.34" waitingTime="4.00" waitingCount="1" stopTime="0.00" timeLoss="19.45" rerouteNo="1" devices="tripinfo_20 routing_20" vType="DEFAULT_VEHTYPE" speedFactor="1.02" vaporized=""/>
    <tripinfo id="25" depart="87.00" departLane="E3_4_WB_0" departPos="5.10" departSpeed="0.00" departDelay="0.33" arrival="149.00" arrivalLane="E3_6_SEB_0" arrivalPos="196.67" arrivalSpeed="5.81" duration="62.00" routeLength="571.87" waitingTime="0.00" waitingCount="0" stopTime="0.00" timeLoss="12.56" rerouteNo="1" devices="tripinfo_25 routing_25" vType="DEFAULT_VEHTYPE" speedFactor="0.87" vaporized=""/>
    <tripinfo id="27" depart="94.00" departLane="E6_7_SWB_0" departPos="5.10" departSpeed="0.00" departDelay="0.40" arrival="151.00" arrivalLane="E3_6_NWB_0" arrivalPos="196.67" arrivalSpeed="12.47" duration="57.00" routeLength="630.87" waitingTime="0.00" waitingCount="0" stopTime="0.00" timeLoss="7.37" rerouteNo="1" devices="tripinfo_27 routing_27" vType="DEFAULT_VEHTYPE" speedFactor="0.95" vaporized=""/>
    <tripinfo id="36" depart="125.00" departLane="E4_5_WB_0" departPos="5.10" departSpeed="0.00" departDelay="0.20" arrival="168.00" arrivalLane="E2_6_NB_0" arrivalPos="175.06" arrivalSpeed="12.24" duration="43.00" routeLength="471.79" waitingTime="0.00" waitingCount="0" stopTime="0.00" timeLoss="6.93" rerouteNo="1" devices="tripinfo_36 routing_36" vType="DEFAULT_VEHTYPE" speedFactor="0.97" vaporized=""/>
    <tripinfo id="34" depart="118.00" departLane="E6_7_NEB_0" departPos="5.10" departSpeed="0.00" departDelay="0.13" arrival="170.00" arrivalLane="E4_5_EB_0" arrivalPos="93.69" arrivalSpeed="12.89" duration="52.00" routeLength="537.24" waitingTime="0.00" waitingCount="0" stopTime="0.00" timeLoss="11.10" rerouteNo="1" devices="tripinfo_34 routing_34" vType="DEFAULT_VEHTYPE" speedFactor="0.99" vaporized=""/>
    <tripinfo id="28" depart="98.00" departLane="E3_4_EB_0" departPos="5.10" departSpeed="0.00" departDelay="0.93" arrival="174.00" arrivalLane="E2_6_SB_0" arrivalPos="175.06" arrivalSpeed="14.91" duration="76.00" routeLength="736.17" waitingTime="9.00" waitingCount="1" stopTime="0.00" timeLoss="26.57" rerouteNo="1" devices="tripinfo_28 routing_28" vType="DEFAULT_VEHTYPE" speedFactor="1.13" vaporized=""/>
    <tripinfo id="47" depart="167.00" departLane="E2_3_WB_0" departPos="5.10" departSpeed="0.00" departDelay="4.07" arrival="177.00" arrivalLane="E2_3_WB_0" arrivalPos="83.62" arrivalSpeed="11.85" duration="10.00" routeLength="78.52" waitingTime="0.00" waitingCount="0" stopTime="0.00" timeLoss="2.82" rerouteNo="1" devices="tripinfo_47 routing_47" vType="DEFAULT_VEHTYPE" speedFactor="0.90" vaporized=""/>
    <tripinfo id="38" depart="135.00" departLane="E4_7_SEB_0" departPos="5.10" departSpeed="0.00" departDelay="3.27" arrival="178.00" arrivalLane="E2_3_WB_0" arrivalPos="83.62" arrivalSpeed="15.10" duration="43.00" routeLength="486.97" waitingTime="0.00" waitingCount="0" stopTime="0.00" timeLoss="10.10" rerouteNo="1" devices="tripinfo_38 routing_38" vType="DEFAULT_VEHTYPE" speedFactor="1.10" vaporized=""/>
    <tripinfo id="40" depart="139.00" departLane="E3_6_SEB_0" departPos="5.10" departSpeed="0.00" departDelay="0.33" arrival="185.00" arrivalLane="E2_6_NB_0" arrivalPos="175.06" arrivalSpeed="14.19" duration="46.00" routeLength="468.46" waitingTime="0.00" waitingCount="0" stopTime="0.00" timeLoss="10.98" rerouteNo="1" devices="tripinfo_40 routing_40" vType="DEFAULT_VEHTYPE" speedFactor="1.03" vaporized=""/>
    <tripinfo id="32" depart="111.00" departLane="E4_7_NWB_0" departPos="5.10" departSpeed="0.00" departDelay="0.07" arrival="190.00" arrivalLane="E2_3_EB_0" arrivalPos="83.62" arrivalSpeed="6.18" duration="79.00" routeLength="732.81" waitingTime="6.00" waitingCount="1" stopTime="0.00" timeLoss="24.79" rerouteNo="1" devices="tripinfo_32 routing_32" vType="DEFAULT_VEHTYPE" speedFactor="1.01" vaporized=""/>
    <tripinfo id="39" depart="143.00" departLane="E4_7_SEB_0" departPos="5.10" departSpeed="0.00" departDelay="7.80" arrival="190.00" arrivalLane="E2_3_WB_0" arrivalPos="83.62" arrivalSpeed="12.31" duration="47.00" routeLength="486.97" waitingTime="0.00" waitingCount="0" stopTime="0.00" timeLoss="6.85" rerouteNo="1" devices="tripinfo_39 routing_39" vType="DEFAULT_VEHTYPE" speedFactor="0.90" vaporized=""/>
    <tripinfo id="30" depart="104.00" departLane="E4_7_NWB_0" departPos="5.10" departSpeed="0.00" departDelay="0.00" arrival="195.00" arrivalLane="E3_6_SEB_0" arrivalPos="196.67" arrivalSpeed="5.37" duration="91.00" routeLength="656.07" waitingTime="29.00" waitingCount="2" stopTime="0.00" timeLoss="49.60" rerouteNo="1" devices="tripinfo_30 routing_30" vType="DEFAULT_VEHTYPE" speedFactor="1.18" vaporized=""/>
    <tripinfo id="14" depart="54.00" departLane="E4_7_SEB_0" departPos="5.10" departSpeed="0.00" departDelay="5.47" arrival="196.00" arrivalLane="E6_7_SWB_0" arrivalPos="125.94" arrivalSpeed="13.75" duration="142.00" routeLength="1437.15" waitingTime="0.00" waitingCount="0" stopTime="0.00" timeLoss="32.14" rerouteNo="1" devices="tripinfo_14 routing_14" vType="DEFAULT_VEHTYPE" speedFactor="0.99" vaporized=""/>
    <tripinfo id="26" depart="91.00" departLane="E2_3_EB_0" departPos="5.10" departSpeed="0.00" departDelay="0.87" arrival="198.00" arrivalLane="E3_6_SEB_0" arrivalPos="196.67" arrivalSpeed="7.50" duration="107.00" routeLength="856.02" waitingTime="12.00" waitingCount="2" stopTime="0.00" timeLoss="37.16" rerouteNo="1" devices="tripinfo_26 routing_26" vType="DEFAULT_VEHTYPE" speedFactor="0.92" vaporized=""/>
    <tripinfo id="29" depart="106.00" departLane="E3_4_EB_0" departPos="5.10" departSpeed="0.00" departDelay="5.47" arrival="200.00" arrivalLane="E3_6_SEB_0" arrivalPos="196.67" arrivalSpeed="8.23" duration="94.00" routeLength="757.24" waitingTime="7.00" waitingCount="2" stopTime="0.00" timeLoss="33.28" rerouteNo="1" devices="tripinfo_29 routing_29" vType="DEFAULT_VEHTYPE" speedFactor="0.93" vaporized=""/>
    <tripinfo id="16" depart="57.00" departLane="E6_7_NEB_0" departPos="5.10" departSpeed="0.00" departDelay="1.53" arrival="202.00" arrivalLane="E4_7_NWB_0" arrivalPos="298.61" arrivalSpeed="11.41" duration="145.00" routeLength="1429.93" waitingTime="0.00" waitingCount="0" stopTime="0.00" timeLoss="21.22" rerouteNo="1" devices="tripinfo_16 routing_16" vType="DEFAULT_VEHTYPE" speedFactor="0.88" vaporized=""/>
    <tripinfo id="35" depart="122.00" departLane="E2_3_WB_0" departPos="5.10" departSpeed="0.00" departDelay="0.67" arrival="202.00" arrivalLane="E3_4_EB_0" arrivalPos="85.58" arrivalSpeed="14.09" duration="80.00" routeLength="572.16" waitingTime="19.00" waitingCount="1" stopTime="0.00" timeLoss="36.67" rerouteNo="1" devices="tripinfo_35 routing_35" vType="DEFAULT_VEHTYPE" speedFactor="1.02" vaporized=""/>
    <tripinfo id="42" depart="146.00" departLane="E2_6_SB_0" departPos="5.10" departSpeed="0.00" departDelay="0.40" arrival="203.00" arrivalLane="E4_7_NWB_0" arrivalPos="298.61" arrivalSpeed="13.29" duration="57.00" routeLength="682.71" waitingTime="0.00" waitingCount="0" stopTime="0.00" timeLoss="10.35" rerouteNo="1" devices="tripinfo_42 routing_42" vType="DEFAULT_VEHTYPE" speedFactor="1.09" vaporized=""/>
    <tripinfo id="53" depart="186.00" departLane="E3_4_WB_0" departPos="5.10" departSpeed="0.00" departDelay="2.27" arrival="211.00" arrivalLane="E3_6_NWB_0" arrivalPos="196.67" arrivalSpeed="14.62" duration="25.00" routeLength="289.06" waitingTime="0.00" waitingCount="0" stopTime="0.00" timeLoss="5.25" rerouteNo="0" devices="tripinfo_53 routing_53" vType="DEFAULT_VEHTYPE" speedFactor="1.10" vaporized=""/>
    <tripinfo id="44" depart="157.00" departLane="E2_3_WB_0" departPos="5.10" departSpeed="0.00" departDelay="4.47" arrival="215.00" arrivalLane="E7_8_NEB_0" arrivalPos="135.44" arrivalSpeed="14.39" duration="58.00" routeLength="560.87" waitingTime="3.00" waitingCount="1" stopTime="0.00" timeLoss="18.46" rerouteNo="1" devices="tripinfo_44 routing_44" vType="DEFAULT_VEHTYPE" speedFactor="1.04" vaporized=""/>
    <tripinfo id="24" depart="88.00" departLane="E2_6_NB_0" departPos="5.10" departSpeed="0.00" departDelay="4.80" arrival="217.00" arrivalLane="E2_3_EB_0" arrivalPos="83.62" arrivalSpeed="11.43" duration="129.00" routeLength="1216.83" waitingTime="0.00" waitingCount="0" stopTime="0.00" timeLoss="17.13" rerouteNo="1" devices="tripinfo_24 routing_24" vType="DEFAULT_VEHTYPE" speedFactor="0.83" vaporized=""/>
    <tripinfo id="33" depart="115.00" departLane="E2_6_NB_0" departPos="5.10" departSpeed="0.00" departDelay="0.60" arrival="218.00" arrivalLane="E2_3_EB_0" arrivalPos="83.62" arrivalSpeed="12.75" duration="103.00" routeLength="1216.83" waitingTime="0.00" waitingCount="0" stopTime="0.00" timeLoss="25.10" rerouteNo="1" devices="tripinfo_33 routing_33" vType="DEFAULT_VEHTYPE" speedFactor="1.17" vaporized=""/>
    <tripinfo id="55" depart="192.00" departLane="E3_4_WB_0" departPos="5.10" departSpeed="0.00" departDelay="1.33" arrival="226.00" arrivalLane="E2_6_NB_0" arrivalPos="175.06" arrivalSpeed="13.26" duration="34.00" routeLength="363.35" waitingTime="0.00" waitingCount="0" stopTime="0.00" timeLoss="6.56" rerouteNo="1" devices="tripinfo_55 routing_55" vType="DEFAULT_VEHTYPE" speedFactor="1.00" vaporized=""/>
    <tripinfo id="57" depart="198.00" departLane="E6_7_NEB_0" departPos="5.10" departSpeed="0.00" departDelay="0.40" arrival="226.00" arrivalLane="E7_8_NEB_0" arrivalPos="135.44" arrivalSpeed="15.36" duration="28.00" routeLength="271.44" waitingTime="0.00" waitingCount="0" stopTime="0.00" timeLoss="10.39" rerouteNo="0" devices="tripinfo_57 routing_57" vType="DEFAULT_VEHTYPE" speedFactor="1.14" vaporized=""/>
    <tripinfo id="41" depart="143.00" departLane="E3_4_WB_0" departPos="5.10" departSpeed="0.00" departDelay="0.87" arrival="232.00" arrivalLane="E4_5_EB_0" arrivalPos="93.69" arrivalSpeed="12.57" duration="89.00" routeLength="781.34" waitingTime="9.00" waitingCount="1" stopTime="0.00" timeLoss="27.19" rerouteNo="1" devices="tripinfo_41 routing_41" vType="DEFAULT_VEHTYPE" speedFactor="0.96" vaporized=""/>
    <tripinfo id="50" depart="176.00" departLane="E3_4_WB_0" departPos="5.10" departSpeed="0.00" departDelay="2.67" arrival="236.00" arrivalLane="E3_6_SEB_0" arrivalPos="196.67" arrivalSpeed="11.16" duration="60.00" routeLength="571.87" waitingTime="0.00" waitingCount="0" stopTime="0.00" timeLoss="9.08" rerouteNo="1" devices="tripinfo_50 routing_50" vType="DEFAULT_VEHTYPE" speedFactor="0.85" vaporized=""/>
    <tripinfo id="48" depart="167.00" departLane="E4_7_NWB_0" departPos="5.10" departSpeed="0.00" departDelay="0.60" arrival="238.00" arrivalLane="E3_6_SEB_0" arrivalPos="196.67" arrivalSpeed="11.27" duration="71.00" routeLength="656.07" waitingTime="2.00" waitingCount="1" stopTime="0.00" timeLoss="14.58" rerouteNo="1" devices="tripinfo_48 routing_48" vType="DEFAULT_VEHTYPE" speedFactor="0.88" vaporized=""/>
    <tripinfo id="54" depart="188.00" departLane="E6_7_NEB_0" departPos="5.10" departSpeed="0.00" departDelay="0.80" arrival="241.00" arrivalLane="E4_5_EB_0" arrivalPos="93.69" arrivalSpeed="13.33" duration="53.00" routeLength="537.24" waitingTime="0.00" waitingCount="0" stopTime="0.00" timeLoss="12.90" rerouteNo="1" devices="tripinfo_54 routing_54" vType="DEFAULT_VEHTYPE" speedFactor="1.00" vaporized=""/>
    <tripinfo id="43" depart="151.00" departLane="E2_6_SB_0" departPos="5.10" departSpeed="0.00" departDelay="1.93" arrival="243.00" arrivalLane="E3_6_SEB_0" arrivalPos="196.67" arrivalSpeed="8.50" duration="92.00" routeLength="1045.27" waitingTime="0.00" waitingCount="0" stopTime="0.00" timeLoss="16.09" rerouteNo="1" devices="tripinfo_43 routing_43" vType="DEFAULT_VEHTYPE" speedFactor="1.04" vaporized=""/>
    <tripinfo id="60" depart="208.00" departLane="E4_7_NWB_0" departPos="5.10" departSpeed="0.00" departDelay="0.00" arrival="243.00" arrivalLane="E7_8_NEB_0" arrivalPos="135.44" arrivalSpeed="14.97" duration="35.00" routeLength="440.86" waitingTime="0.00" waitingCount="0" stopTime="0.00" timeLoss="4.94" rerouteNo="0" devices="tripinfo_60 routing_60" vType="DEFAULT_VEHTYPE" speedFactor="1.08" vaporized=""/>
    <tripinfo id="51" depart="177.00" departLane="E2_3_EB_0" departPos="5.10" departSpeed="0.00" departDelay="0.20" arrival="249.00" arrivalLane="E4_7_SEB_0" arrivalPos="298.61" arrivalSpeed="6.42" duration="72.00" routeLength="744.96" waitingTime="0.00" waitingCount="0" stopTime="0.00" timeLoss="24.46" rerouteNo="1" devices="tripinfo_51 routing_51" vType="DEFAULT_VEHTYPE" speedFactor="1.17" vaporized=""/>
    <tripinfo id="46" depart="160.00" departLane="E3_4_EB_0" departPos="5.10" departSpeed="0.00" departDelay="0.53" arrival="250.00" arrivalLane="E2_3_WB_0" arrivalPos="83.62" arrivalSpeed="13.20" duration="90.00" routeLength="850.04" waitingTime="1.00" waitingCount="1" stopTime="0.00" timeLoss="24.61" rerouteNo="1" devices="tripinfo_46 routing_46" vType="DEFAULT_VEHTYPE" speedFactor="1.00" vaporized=""/>
    <tripinfo id="37" depart="130.00" departLane="E2_3_WB_0" departPos="5.10" departSpeed="0.00" departDelay="1.73" arrival="251.00" arrivalLane="E2_3_EB_0" arrivalPos="83.62" arrivalSpeed="16.17" duration="121.00" routeLength="1309.48" waitingTime="11.00" waitingCount="1" stopTime="0.00" timeLoss="38.09" rerouteNo="1" devices="tripinfo_37 routing_37" vType="DEFAULT_VEHTYPE" speedFactor="1.18" vaporized=""/>
    <tripinfo id="58" depart="202.00" departLane="E2_3_EB_0" departPos="5.10" departSpeed="0.00" departDelay="0.93" arrival="259.00" arrivalLane="E7_8_NEB_0" arrivalPos="135.44" arrivalSpeed="13.72" duration="57.00" routeLength="640.81" waitingTime="0.00" waitingCount="0" stopTime="0.00" timeLoss="10.27" rerouteNo="1" devices="tripinfo_58 routing_58" vType="DEFAULT_VEHTYPE" speedFactor="1.02" vaporized=""/>
    <tripinfo id="45" depart="163.00" departLane="E2_3_WB_0" departPos="5.10" departSpeed="0.00" departDelay="7.00" arrival="262.00" arrivalLane="E6_7_SWB_0" arrivalPos="125.94" arrivalSpeed="14.47" duration="99.00" routeLength="1028.70" waitingTime="5.00" waitingCount="1" stopTime="0.00" timeLoss="26.95" rerouteNo="1" devices="tripinfo_45 routing_45" vType="DEFAULT_VEHTYPE" speedFactor="1.09" vaporized=""/>
    <tripinfo id="61" depart="212.00" departLane="E6_7_NEB_0" departPos="5.10" departSpeed="0.00" departDelay="0.53" arrival="268.00" arrivalLane="E2_3_WB_0" arrivalPos="83.62" arrivalSpeed="15.10" duration="56.00" routeLength="622.09" waitingTime="0.00" waitingCount="0" stopTime="0.00" timeLoss="13.62" rerouteNo="1" devices="tripinfo_61 routing_61" vType="DEFAULT_VEHTYPE" speedFactor="1.12" vaporized=""/>
    <tripinfo id="56" depart="195.00" departLane="E6_7_NEB_0" departPos="5.10" departSpeed="0.00" departDelay="0.87" arrival="275.00" arrivalLane="E2_6_NB_0" arrivalPos="175.06" arrivalSpeed="11.71" duration="80.00" routeLength="806.18" waitingTime="0.00" waitingCount="0" stopTime="0.00" timeLoss="12.34" rerouteNo="1" devices="tripinfo_56 routing_56" vType="DEFAULT_VEHTYPE" speedFactor="0.90" vaporized=""/>
    <tripinfo id="65" depart="226.00" departLane="E1_2_EB_0" departPos="5.10" departSpeed="0.00" departDelay="0.67" arrival="276.00" arrivalLane="E3_6_SEB_0" arrivalPos="196.67" arrivalSpeed="12.06" duration="50.00" routeLength="485.47" waitingTime="0.00" waitingCount="0" stopTime="0.00" timeLoss="7.95" rerouteNo="1" devices="tripinfo_65 routing_65" vType="DEFAULT_VEHTYPE" speedFactor="0.88" vaporized=""/>
    <tripinfo id="72" depart="250.00" departLane="E6_7_NEB_0" departPos="5.10" departSpeed="0.00" departDelay="0.40" arrival="277.00" arrivalLane="E7_8_NEB_0" arrivalPos="135.44" arrivalSpeed="11.88" duration="27.00" routeLength="271.44" waitingTime="0.00" waitingCount="0" stopTime="0.00" timeLoss="5.43" rerouteNo="0" devices="tripinfo_72 routing_72" vType="DEFAULT_VEHTYPE" speedFactor="0.94" vaporized=""/>
    <tripinfo id="71" depart="247.00" departLane="E3_6_NWB_0" departPos="5.10" departSpeed="0.00" departDelay="0.87" arrival="279.00" arrivalLane="E6_7_NEB_0" arrivalPos="125.94" arrivalSpeed="13.37" duration="32.00" routeLength="337.15" waitingTime="0.00" waitingCount="0" stopTime="0.00" timeLoss="6.28" rerouteNo="0" devices="tripinfo_71 routing_71" vType="DEFAULT_VEHTYPE" speedFactor="0.97" vaporized=""/>
    <tripinfo id="52" depart="181.00" departLane="E2_6_SB_0" departPos="5.10" departSpeed="0.00" departDelay="0.73" arrival="280.00" arrivalLane="E3_4_WB_0" arrivalPos="85.58" arrivalSpeed="11.41" duration="99.00" routeLength="1028.89" waitingTime="0.00" waitingCount="0" stopTime="0.00" timeLoss="22.89" rerouteNo="1" devices="tripinfo_52 routing_52" vType="DEFAULT_VEHTYPE" speedFactor="1.02" vaporized=""/>
    <tripinfo id="64" depart="222.00" departLane="E1_2_EB_0" departPos="5.10" departSpeed="0.00" departDelay="0.13" arrival="281.00" arrivalLane="E2_6_SB_0" arrivalPos="175.06" arrivalSpeed="12.76" duration="59.00" routeLength="589.14" waitingTime="0.00" waitingCount="0" stopTime="0.00" timeLoss="10.50" rerouteNo="1" devices="tripinfo_64 routing_64" vType="DEFAULT_VEHTYPE" speedFactor="0.94" vaporized=""/>
    <tripinfo id="78" depart="271.00" departLane="E3_6_SEB_0" departPos="5.10" departSpeed="0.00" departDelay="0.60" arrival="289.00" arrivalLane="E3_6_SEB_0" arrivalPos="196.67" arrivalSpeed="13.13" duration="18.00" routeLength="191.57" waitingTime="0.00" waitingCount="0" stopTime="0.00" timeLoss="3.47" rerouteNo="1" devices="tripinfo_78 routing_78" vType="DEFAULT_VEHTYPE" speedFactor="1.01" vaporized=""/>
    <tripinfo id="62" depart="215.00" departLane="E3_6_NWB_0" departPos="5.10" departSpeed="0.00" departDelay="0.07" arrival="305.00" arrivalLane="E4_7_NWB_0" arrivalPos="298.61" arrivalSpeed="12.84" duration="90.00" routeLength="894.67" waitingTime="0.00" waitingCount="0" stopTime="0.00" timeLoss="23.70" rerouteNo="1" devices="tripinfo_62 routing_62" vType="DEFAULT_VEHTYPE" speedFactor="1.02" vaporized=""/>
    <tripinfo id="63" depart="219.00" departLane="E4_7_NWB_0" departPos="5.10" departSpeed="0.00" departDelay="0.60" arrival="305.00" arrivalLane="E2_6_NB_0" arrivalPos="175.06" arrivalSpeed="13.03" duration="86.00" routeLength="932.96" waitingTime="0.00" waitingCount="0" stopTime="0.00" timeLoss="13.94" rerouteNo="1" devices="tripinfo_63 routing_63" vType="DEFAULT_VEHTYPE" speedFactor="0.99" vaporized=""/>
    <tripinfo id="67" depart="233.00" departLane="E4_5_WB_0" departPos="5.10" departSpeed="0.00" departDelay="0.73" arrival="310.00" arrivalLane="E2_3_EB_0" arrivalPos="83.62" arrivalSpeed="4.12" duration="77.00" routeLength="685.66" waitingTime="6.00" waitingCount="1" stopTime="0.00" timeLoss="19.82" rerouteNo="1" devices="tripinfo_67 routing_67" vType="DEFAULT_VEHTYPE" speedFactor="0.91" vaporized=""/>
    <tripinfo id="68" depart="236.00" departLane="E3_6_SEB_0" departPos="5.10" departSpeed="0.00" departDelay="0.27" arrival="315.00" arrivalLane="E4_7_SEB_0" arrivalPos="298.61" arrivalSpeed="13.48" duration="79.00" routeLength="923.91" waitingTime="0.00" waitingCount="0" stopTime="0.00" timeLoss="12.57" rerouteNo="1" devices="tripinfo_68 routing_68" vType="DEFAULT_VEHTYPE" speedFactor="1.04" vaporized=""/>
    <tripinfo id="80" depart="278.00" departLane="E6_7_SWB_0" departPos="5.10" departSpeed="0.00" departDelay="0.67" arrival="319.00" arrivalLane="E2_3_EB_0" arrivalPos="83.62" arrivalSpeed="8.59" duration="41.00" routeLength="417.80" waitingTime="0.00" waitingCount="0" stopTime="0.00" timeLoss="11.05" rerouteNo="1" devices="tripinfo_80 routing_80" vType="DEFAULT_VEHTYPE" speedFactor="1.03" vaporized=""/>
    <tripinfo id="84" depart="292.00" departLane="E3_6_SEB_0" departPos="5.10" departSpeed="0.00" departDelay="0.80" arrival="321.00" arrivalLane="E2_3_WB_0" arrivalPos="83.62" arrivalSpeed="11.95" duration="29.00" routeLength="284.37" waitingTime="0.00" waitingCount="0" stopTime="0.00" timeLoss="10.00" rerouteNo="0" devices="tripinfo_84 routing_84" vType="DEFAULT_VEHTYPE" speedFactor="1.15" vaporized=""/>
    <tripinfo id="88" depart="308.00" departLane="E6_7_SWB_0" departPos="5.10" departSpeed="0.00" departDelay="2.93" arrival="339.00" arrivalLane="E6_7_SWB_0" arrivalPos="125.94" arrivalSpeed="4.17" duration="31.00" routeLength="120.84" waitingTime="14.00" waitingCount="1" stopTime="0.00" timeLoss="22.13" rerouteNo="1" devices="tripinfo_88 routing_88" vType="DEFAULT_VEHTYPE" speedFactor="1.01" vaporized=""/>
    <tripinfo id="73" depart="255.00" departLane="E6_7_NEB_0" departPos="5.10" departSpeed="0.00" departDelay="1.93" arrival="347.00" arrivalLane="E3_6_SEB_0" arrivalPos="196.67" arrivalSpeed="14.49" duration="92.00" routeLength="1014.70" waitingTime="0.00" waitingCount="0" stopTime="0.00" timeLoss="18.12" rerouteNo="1" devices="tripinfo_73 routing_73" vType="DEFAULT_VEHTYPE" speedFactor="1.06" vaporized=""/>
    <tripinfo id="66" depart="232.00" departLane="E2_6_SB_0" departPos="5.10" departSpeed="0.00" departDelay="3.20" arrival="358.00" arrivalLane="E3_6_SEB_0" arrivalPos="196.67" arrivalSpeed="11.95" duration="126.00" routeLength="1045.27" waitingTime="18.00" waitingCount="2" stopTime="0.00" timeLoss="39.02" rerouteNo="1" devices="tripinfo_66 routing_66" vType="DEFAULT_VEHTYPE" speedFactor="0.91" vaporized=""/>
    <tripinfo id="81" depart="281.00" departLane="E3_6_SEB_0" departPos="5.10" departSpeed="0.00" departDelay="0.20" arrival="363.00" arrivalLane="E4_7_SEB_0" arrivalPos="298.61" arrivalSpeed="13.53" duration="82.00" routeLength="923.91" waitingTime="0.00" waitingCount="0" stopTime="0.00" timeLoss="12.99" rerouteNo="1" devices="tripinfo_81 routing_81" vType="DEFAULT_VEHTYPE" speedFactor="1.00" vaporized=""/>
    <tripinfo id="93" depart="323.00" departLane="E1_2_EB_0" departPos="5.10" departSpeed="0.00" departDelay="0.60" arrival="364.00" arrivalLane="E2_6_NB_0" arrivalPos="175.06" arrivalSpeed="12.25" duration="41.00" routeLength="276.95" waitingTime="10.00" waitingCount="1" stopTime="0.00" timeLoss="17.95" rerouteNo="0" devices="tripinfo_93 routing_93" vType="DEFAULT_VEHTYPE" speedFactor="0.92" vaporized=""/>
    <tripinfo id="49" depart="173.00" departLane="E2_3_WB_0" departPos="5.10" departSpeed="0.00" departDelay="3.13" arrival="373.00" arrivalLane="E2_3_EB_0" arrivalPos="83.62" arrivalSpeed="10.91" duration="200.00" routeLength="1309.48" waitingTime="58.00" waitingCount="1" stopTime="0.00" timeLoss="83.69" rerouteNo="1" devices="tripinfo_49 routing_49" vType="DEFAULT_VEHTYPE" speedFactor="0.85" vaporized=""/>
    <tripinfo id="95" depart="330.00" departLane="E2_3_WB_0" departPos="5.10" departSpeed="0.00" departDelay="0.67" arrival="377.00" arrivalLane="E7_8_NEB_0" arrivalPos="135.44" arrivalSpeed="13.45" duration="47.00" routeLength="560.87" waitingTime="0.00" waitingCount="0" stopTime="0.00" timeLoss="8.00" rerouteNo="1" devices="tripinfo_95 routing_95" vType="DEFAULT_VEHTYPE" speedFactor="1.06" vaporized=""/>
    <tripinfo id="104" depart="361.00" departLane="E2_3_EB_0" departPos="5.10" departSpeed="0.00" departDelay="0.47" arrival="377.00" arrivalLane="E3_4_EB_0" arrivalPos="85.58" arrivalSpeed="14.06" duration="16.00" routeLength="179.26" waitingTime="0.00" waitingCount="0" stopTime="0.00" timeLoss="3.72" rerouteNo="0" devices="tripinfo_104 routing_104" vType="DEFAULT_VEHTYPE" speedFactor="1.07" vaporized=""/>
    <tripinfo id="85" depart="295.00" departLane="E2_3_WB_0" departPos="5.10" departSpeed="0.00" departDelay="0.33" arrival="380.00" arrivalLane="E4_7_NWB_0" arrivalPos="298.61" arrivalSpeed="8.72" duration="85.00" routeLength="886.36" waitingTime="0.00" waitingCount="0" stopTime="0.00" timeLoss="16.87" rerouteNo="1" devices="tripinfo_85 routing_85" vType="DEFAULT_VEHTYPE" speedFactor="0.98" vaporized=""/>
    <tripinfo id="77" depart="268.00" departLane="E3_4_WB_0" departPos="5.10" departSpeed="0.00" departDelay="1.07" arrival="381.00" arrivalLane="E3_6_NWB_0" arrivalPos="196.67" arrivalSpeed="4.94" duration="113.00" routeLength="289.06" waitingTime="78.00" waitingCount="2" stopTime="0.00" timeLoss="91.08" rerouteNo="0" devices="tripinfo_77 routing_77" vType="DEFAULT_VEHTYPE" speedFactor="0.98" vaporized=""/>
    <tripinfo id="89" depart="309.00" departLane="E2_3_WB_0" departPos="5.10" departSpeed="0.00" departDelay="0.47" arrival="386.00" arrivalLane="E3_4_WB_0" arrivalPos="85.58" arrivalSpeed="13.19" duration="77.00" routeLength="812.74" waitingTime="3.00" waitingCount="1" stopTime="0.00" timeLoss="17.76" rerouteNo="1" devices="tripinfo_89 routing_89" vType="DEFAULT_VEHTYPE" speedFactor="1.02" vaporized=""/>
    <tripinfo id="86" depart="299.00" departLane="E3_6_SEB_0" departPos="5.10" departSpeed="0.00" departDelay="0.87" arrival="391.00" arrivalLane="E2_6_SB_0" arrivalPos="175.06" arrivalSpeed="12.65" duration="92.00" routeLength="948.29" waitingTime="1.00" waitingCount="1" stopTime="0.00" timeLoss="21.51" rerouteNo="1" devices="tripinfo_86 routing_86" vType="DEFAULT_VEHTYPE" speedFactor="1.00" vaporized=""/>
    <tripinfo id="94" depart="326.00" departLane="E2_3_WB_0" departPos="5.10" departSpeed="0.00" departDelay="0.13" arrival="391.00" arrivalLane="E4_7_SEB_0" arrivalPos="298.61" arrivalSpeed="6.18" duration="65.00" routeLength="718.06" waitingTime="0.00" waitingCount="0" stopTime="0.00" timeLoss="16.13" rerouteNo="1" devices="tripinfo_94 routing_94" vType="DEFAULT_VEHTYPE" speedFactor="1.09" vaporized=""/>
    <tripinfo id="69" depart="240.00" departLane="E1_2_EB_0" departPos="5.10" departSpeed="0.00" departDelay="0.80" arrival="395.00" arrivalLane="E2_6_SB_0" arrivalPos="175.06" arrivalSpeed="13.36" duration="155.00" routeLength="589.14" waitingTime="91.00" waitingCount="3" stopTime="0.00" timeLoss="111.42" rerouteNo="1" devices="tripinfo_69 routing_69" vType="DEFAULT_VEHTYPE" speedFactor="1.02" vaporized=""/>
    <tripinfo id="103" depart="358.00" departLane="E3_4_EB_0" departPos="5.10" departSpeed="0.00" departDelay="0.93" arrival="395.00" arrivalLane="E4_7_NWB_0" arrivalPos="298.61" arrivalSpeed="12.91" duration="37.00" routeLength="394.68" waitingTime="0.00" waitingCount="0" stopTime="0.00" timeLoss="6.47" rerouteNo="0" devices="tripinfo_103 routing_103" vType="DEFAULT_VEHTYPE" speedFactor="0.95" vaporized=""/>
    <tripinfo id="91" depart="316.00" departLane="E1_2_EB_0" departPos="5.10" departSpeed="0.00" departDelay="0.53" arrival="399.00" arrivalLane="E3_4_WB_0" arrivalPos="85.58" arrivalSpeed="12.37" duration="83.00" routeLength="827.08" waitingTime="0.00" waitingCount="0" stopTime="0.00" timeLoss="13.27" rerouteNo="1" devices="tripinfo_91 routing_91" vType="DEFAULT_VEHTYPE" speedFactor="0.89" vaporized=""/>
    <tripinfo id="59" depart="205.00" departLane="E3_6_SEB_0" departPos="5.10" departSpeed="0.00" departDelay="0.47" arrival="406.00" arrivalLane="E3_6_NWB_0" arrivalPos="196.67" arrivalSpeed="5.33" duration="201.00" routeLength="1227.17" waitingTime="65.00" waitingCount="3" stopTime="0.00" timeLoss="105.97" rerouteNo="1" devices="tripinfo_59 routing_59" vType="DEFAULT_VEHTYPE" speedFactor="0.97" vaporized=""/>
    <tripinfo id="108" depart="377.00" departLane="E3_6_SEB_0" departPos="5.10" departSpeed="0.00" departDelay="2.60" arrival="406.00" arrivalLane="E2_3_WB_0" arrivalPos="83.62" arrivalSpeed="12.51" duration="29.00" routeLength="284.37" waitingTime="0.00" waitingCount="0" stopTime="0.00" timeLoss="6.51" rerouteNo="0" devices="tripinfo_108 routing_108" vType="DEFAULT_VEHTYPE" speedFactor="0.96" vaporized=""/>
    <tripinfo id="96" depart="333.00" departLane="E2_3_WB_0" departPos="5.10" departSpeed="0.00" departDelay="0.20" arrival="407.00" arrivalLane="E3_4_WB_0" arrivalPos="85.58" arrivalSpeed="13.07" duration="74.00" routeLength="812.74" waitingTime="0.00" waitingCount="0" stopTime="0.00" timeLoss="13.19" rerouteNo="1" devices="tripinfo_96 routing_96" vType="DEFAULT_VEHTYPE" speedFactor="1.01" vaporized=""/>
    <tripinfo id="109" depart="382.00" departLane="E6_7_SWB_0" departPos="5.10" departSpeed="0.00" departDelay="4.13" arrival="414.00" arrivalLane="E3_6_SEB_0" arrivalPos="196.67" arrivalSpeed="12.07" duration="32.00" routeLength="341.06" waitingTime="0.00" waitingCount="0" stopTime="0.00" timeLoss="4.71" rerouteNo="0" devices="tripinfo_109 routing_109" vType="DEFAULT_VEHTYPE" speedFactor="0.93" vaporized=""/>
    <tripinfo id="74" depart="257.00" departLane="E4_7_SEB_0" departPos="5.10" departSpeed="0.00" departDelay="0.47" arrival="418.00" arrivalLane="E2_6_SB_0" arrivalPos="175.06" arrivalSpeed="13.08" duration="161.00" routeLength="787.12" waitingTime="71.00" waitingCount="3" stopTime="0.00" timeLoss="98.51" rerouteNo="1" devices="tripinfo_74 routing_74" vType="DEFAULT_VEHTYPE" speedFactor="0.96" vaporized=""/>
    <tripinfo id="112" depart="389.00" departLane="E3_6_SEB_0" departPos="5.10" departSpeed="0.00" departDelay="0.73" arrival="418.00" arrivalLane="E3_4_EB_0" arrivalPos="85.58" arrivalSpeed="13.72" duration="29.00" routeLength="292.60" waitingTime="0.00" waitingCount="0" stopTime="0.00" timeLoss="7.22" rerouteNo="0" devices="tripinfo_112 routing_112" vType="DEFAULT_VEHTYPE" speedFactor="1.01" vaporized=""/>
    <tripinfo id="99" depart="350.00" departLane="E2_6_NB_0" departPos="5.10" departSpeed="0.00" departDelay="6.80" arrival="419.00" arrivalLane="E4_7_NWB_0" arrivalPos="298.61" arrivalSpeed="11.71" duration="69.00" routeLength="793.71" waitingTime="0.00" waitingCount="0" stopTime="0.00" timeLoss="14.13" rerouteNo="1" devices="tripinfo_99 routing_99" vType="DEFAULT_VEHTYPE" speedFactor="1.10" vaporized=""/>
    <tripinfo id="98" depart="340.00" departLane="E3_4_EB_0" departPos="5.10" departSpeed="0.00" departDelay="0.27" arrival="420.00" arrivalLane="E2_3_WB_0" arrivalPos="83.62" arrivalSpeed="14.38" duration="80.00" routeLength="850.04" waitingTime="0.00" waitingCount="0" stopTime="0.00" timeLoss="21.70" rerouteNo="1" devices="tripinfo_98 routing_98" vType="DEFAULT_VEHTYPE" speedFactor="1.12" vaporized=""/>
    <tripinfo id="100" depart="347.00" departLane="E6_7_SWB_0" departPos="5.10" departSpeed="0.00" departDelay="0.33" arrival="421.00" arrivalLane="E4_7_NWB_0" arrivalPos="298.61" arrivalSpeed="14.00" duration="74.00" routeLength="756.29" waitingTime="5.00" waitingCount="1" stopTime="0.00" timeLoss="21.30" rerouteNo="1" devices="tripinfo_100 routing_100" vType="DEFAULT_VEHTYPE" speedFactor="1.06" vaporized=""/>
    <tripinfo id="105" depart="364.00" departLane="E4_5_WB_0" departPos="5.10" departSpeed="0.00" departDelay="0.00" arrival="421.00" arrivalLane="E6_7_NEB_0" arrivalPos="125.94" arrivalSpeed="13.79" duration="57.00" routeLength="619.45" waitingTime="0.00" waitingCount="0" stopTime="0.00" timeLoss="11.86" rerouteNo="1" devices="tripinfo_105 routing_105" vType="DEFAULT_VEHTYPE" speedFactor="1.01" vaporized=""/>
    <tripinfo id="113" depart="392.00" departLane="E4_5_WB_0" departPos="5.10" departSpeed="0.00" departDelay="0.27" arrival="425.00" arrivalLane="E4_7_NWB_0" arrivalPos="298.61" arrivalSpeed="14.55" duration="33.00" routeLength="398.10" waitingTime="0.00" waitingCount="0" stopTime="0.00" timeLoss="6.16" rerouteNo="0" devices="tripinfo_113 routing_113" vType="DEFAULT_VEHTYPE" speedFactor="1.10" vaporized=""/>
    <tripinfo id="79" depart="274.00" departLane="E2_3_EB_0" departPos="5.10" departSpeed="0.00" departDelay="0.13" arrival="429.00" arrivalLane="E3_4_WB_0" arrivalPos="85.58" arrivalSpeed="14.16" duration="155.00" routeLength="839.64" waitingTime="72.00" waitingCount="2" stopTime="0.00" timeLoss="96.43" rerouteNo="1" devices="tripinfo_79 routing_79" vType="DEFAULT_VEHTYPE" speedFactor="1.09" vaporized=""/>
    <tripinfo id="82" depart="285.00" departLane="E1_2_EB_0" departPos="5.10" departSpeed="0.00" departDelay="0.73" arrival="429.00" arrivalLane="E3_6_NWB_0" arrivalPos="196.67" arrivalSpeed="5.66" duration="144.00" routeLength="398.79" waitingTime="77.00" waitingCount="5" stopTime="0.00" timeLoss="114.42" rerouteNo="1" devices="tripinfo_82 routing_82" vType="DEFAULT_VEHTYPE" speedFactor="1.02" vaporized=""/>
    <tripinfo id="agent" depart="360.00" departLane="E1_2_EB_0" departPos="5.10" departSpeed="0.00" departDelay="0.00" arrival="430.00" arrivalLane="E7_8_NEB_0" arrivalPos="135.44" arrivalSpeed="11.26" duration="70.00" routeLength="748.01" waitingTime="0.00" waitingCount="0" stopTime="0.00" timeLoss="8.33" rerouteNo="0" devices="tripinfo_agent" vType="DEFAULT_VEHTYPE" speedFactor="0.89" vaporized=""/>
    <tripinfo id="101" depart="352.00" departLane="E6_7_SWB_0" departPos="5.10" departSpeed="0.00" departDelay="1.87" arrival="431.00" arrivalLane="E4_7_NWB_0" arrivalPos="298.61" arrivalSpeed="13.23" duration="79.00" routeLength="756.29" waitingTime="3.00" waitingCount="2" stopTime="0.00" timeLoss="20.59" rerouteNo="1" devices="tripinfo_101 routing_101" vType="DEFAULT_VEHTYPE" speedFactor="0.96" vaporized=""/>
    <tripinfo id="116" depart="403.00" departLane="E6_7_NEB_0" departPos="5.10" departSpeed="0.00" departDelay="0.87" arrival="432.00" arrivalLane="E7_8_NEB_0" arrivalPos="135.44" arrivalSpeed="13.50" duration="29.00" routeLength="271.44" waitingTime="0.00" waitingCount="0" stopTime="0.00" timeLoss="8.85" rerouteNo="0" devices="tripinfo_116 routing_116" vType="DEFAULT_VEHTYPE" speedFactor="1.00" vaporized=""/>
    <tripinfo id="115" depart="399.00" departLane="E2_3_EB_0" departPos="5.10" departSpeed="0.00" departDelay="0.33" arrival="437.00" arrivalLane="E4_7_NWB_0" arrivalPos="298.61" arrivalSpeed="15.51" duration="38.00" routeLength="493.46" waitingTime="0.00" waitingCount="0" stopTime="0.00" timeLoss="6.60" rerouteNo="1" devices="tripinfo_115 routing_115" vType="DEFAULT_VEHTYPE" speedFactor="1.18" vaporized=""/>
    <tripinfo id="111" depart="387.00" departLane="E6_7_NEB_0" departPos="5.10" departSpeed="0.00" departDelay="2.20" arrival="438.00" arrivalLane="E4_5_EB_0" arrivalPos="93.69" arrivalSpeed="14.98" duration="51.00" routeLength="537.24" waitingTime="3.00" waitingCount="1" stopTime="0.00" timeLoss="14.85" rerouteNo="1" devices="tripinfo_111 routing_111" vType="DEFAULT_VEHTYPE" speedFactor="1.10" vaporized=""/>
    <tripinfo id="83" depart="288.00" departLane="E3_4_WB_0" departPos="5.10" departSpeed="0.00" departDelay="0.27" arrival="440.00" arrivalLane="E3_4_EB_0" arrivalPos="85.58" arrivalSpeed="13.01" duration="152.00" routeLength="677.96" waitingTime="71.00" waitingCount="3" stopTime="0.00" timeLoss="98.39" rerouteNo="1" devices="tripinfo_83 routing_83" vType="DEFAULT_VEHTYPE" speedFactor="0.97" vaporized=""/>
    <tripinfo id="75" depart="260.00" departLane="E3_4_EB_0" departPos="5.10" departSpeed="0.00" departDelay="0.00" arrival="442.00" arrivalLane="E3_6_NWB_0" arrivalPos="196.67" arrivalSpeed="6.68" duration="182.00" routeLength="1047.05" waitingTime="50.00" waitingCount="4" stopTime="0.00" timeLoss="102.12" rerouteNo="1" devices="tripinfo_75 routing_75" vType="DEFAULT_VEHTYPE" speedFactor="0.98" vaporized=""/>
    <tripinfo id="107" depart="371.00" departLane="E2_6_SB_0" departPos="5.10" departSpeed="0.00" departDelay="0.07" arrival="444.00" arrivalLane="E3_6_NWB_0" arrivalPos="196.67" arrivalSpeed="8.19" duration="73.00" routeLength="480.84" waitingTime="10.00" waitingCount="1" stopTime="0.00" timeLoss="38.56" rerouteNo="1" devices="tripinfo_107 routing_107" vType="DEFAULT_VEHTYPE" speedFactor="1.06" vaporized=""/>
    <tripinfo id="97" depart="337.00" departLane="E3_4_EB_0" departPos="5.10" departSpeed="0.00" departDelay="0.73" arrival="452.00" arrivalLane="E3_6_NWB_0" arrivalPos="196.67" arrivalSpeed="9.22" duration="115.00" routeLength="1047.05" waitingTime="4.00" waitingCount="1" stopTime="0.00" timeLoss="27.92" rerouteNo="1" devices="tripinfo_97 routing_97" vType="DEFAULT_VEHTYPE" speedFactor="0.91" vaporized=""/>
    <tripinfo id="110" depart="385.00" departLane="E4_7_SEB_0" departPos="5.10" departSpeed="0.00" departDelay="3.67" arrival="453.00" arrivalLane="E2_6_NB_0" arrivalPos="175.06" arrivalSpeed="11.36" duration="68.00" routeLength="671.06" waitingTime="0.00" waitingCount="0" stopTime="0.00" timeLoss="9.41" rerouteNo="1" devices="tripinfo_110 routing_110" vType="DEFAULT_VEHTYPE" speedFactor="0.87" vaporized=""/>
    <tripinfo id="90" depart="312.00" departLane="E3_4_EB_0" departPos="5.10" departSpeed="0.00" departDelay="0.00" arrival="462.00" arrivalLane="E3_4_WB_0" arrivalPos="85.58" arrivalSpeed="14.05" duration="150.00" routeLength="1584.26" waitingTime="4.00" waitingCount="1" stopTime="0.00" timeLoss="32.66" rerouteNo="1" devices="tripinfo_90 routing_90" vType="DEFAULT_VEHTYPE" speedFactor="1.02" vaporized=""/>
    <tripinfo id="117" depart="411.00" departLane="E2_6_NB_0" departPos="5.10" departSpeed="0.00" departDelay="5.40" arrival="464.00" arrivalLane="E4_5_EB_0" arrivalPos="93.69" arrivalSpeed="13.66" duration="53.00" routeLength="587.95" waitingTime="0.00" waitingCount="0" stopTime="0.00" timeLoss="8.01" rerouteNo="1" devices="tripinfo_117 routing_117" vType="DEFAULT_VEHTYPE" speedFactor="0.99" vaporized=""/>
    <tripinfo id="114" depart="396.00" departLane="E1_2_EB_0" departPos="5.10" departSpeed="0.00" departDelay="0.80" arrival="465.00" arrivalLane="E4_7_SEB_0" arrivalPos="298.61" arrivalSpeed="12.04" duration="69.00" routeLength="732.40" waitingTime="0.00" waitingCount="0" stopTime="0.00" timeLoss="9.37" rerouteNo="1" devices="tripinfo_114 routing_114" vType="DEFAULT_VEHTYPE" speedFactor="0.92" vaporized=""/>
    <tripinfo id="130" depart="453.00" departLane="E6_7_NEB_0" departPos="5.10" departSpeed="0.00" departDelay="2.33" arrival="465.00" arrivalLane="E6_7_NEB_0" arrivalPos="125.94" arrivalSpeed="14.15" duration="12.00" routeLength="120.84" waitingTime="0.00" waitingCount="0" stopTime="0.00" timeLoss="3.70" rerouteNo="1" devices="tripinfo_130 routing_130" vType="DEFAULT_VEHTYPE" speedFactor="1.07" vaporized=""/>
    <tripinfo id="118" depart="410.00" departLane="E2_6_SB_0" departPos="5.10" departSpeed="0.00" departDelay="0.93" arrival="468.00" arrivalLane="E4_5_EB_0" arrivalPos="93.69" arrivalSpeed="14.66" duration="58.00" routeLength="476.95" waitingTime="13.00" waitingCount="1" stopTime="0.00" timeLoss="24.87" rerouteNo="1" devices="tripinfo_118 routing_118" vType="DEFAULT_VEHTYPE" speedFactor="1.07" vaporized=""/>
    <tripinfo id="70" depart="244.00" departLane="E4_7_NWB_0" departPos="5.10" departSpeed="0.00" departDelay="1.33" arrival="480.00" arrivalLane="E3_4_WB_0" arrivalPos="85.58" arrivalSpeed="13.83" duration="236.00" routeLength="1493.93" waitingTime="71.00" waitingCount="5" stopTime="0.00" timeLoss="126.04" rerouteNo="1" devices="tripinfo_70 routing_70" vType="DEFAULT_VEHTYPE" speedFactor="1.02" vaporized=""/>
    <tripinfo id="128" depart="444.00" departLane="E4_7_NWB_0" departPos="5.10" departSpeed="0.00" departDelay="0.27" arrival="482.00" arrivalLane="E6_7_SWB_0" arrivalPos="125.94" arrivalSpeed="13.50" duration="38.00" routeLength="435.85" waitingTime="0.00" waitingCount="0" stopTime="0.00" timeLoss="6.02" rerouteNo="0" devices="tripinfo_128 routing_128" vType="DEFAULT_VEHTYPE" speedFactor="1.01" vaporized=""/>
    <tripinfo id="121" depart="420.00" departLane="E1_2_EB_0" departPos="5.10" departSpeed="0.00" departDelay="0.53" arrival="485.00" arrivalLane="E6_7_SWB_0" arrivalPos="125.94" arrivalSpeed="13.52" duration="65.00" routeLength="743.00" waitingTime="0.00" waitingCount="0" stopTime="0.00" timeLoss="10.69" rerouteNo="1" devices="tripinfo_121 routing_121" vType="DEFAULT_VEHTYPE" speedFactor="1.03" vaporized=""/>
    <tripinfo id="135" depart="470.00" departLane="E2_3_EB_0" departPos="5.10" departSpeed="0.00" departDelay="2.00" arrival="487.00" arrivalLane="E3_4_EB_0" arrivalPos="85.58" arrivalSpeed="12.80" duration="17.00" routeLength="179.26" waitingTime="0.00" waitingCount="0" stopTime="0.00" timeLoss="4.76" rerouteNo="0" devices="tripinfo_135 routing_135" vType="DEFAULT_VEHTYPE" speedFactor="1.12" vaporized=""/>
    <tripinfo id="123" depart="427.00" departLane="E3_6_NWB_0" departPos="5.10" departSpeed="0.00" departDelay="0.60" arrival="490.00" arrivalLane="E4_7_SEB_0" arrivalPos="298.61" arrivalSpeed="7.17" duration="63.00" routeLength="644.94" waitingTime="0.00" waitingCount="0" stopTime="0.00" timeLoss="18.33" rerouteNo="1" devices="tripinfo_123 routing_123" vType="DEFAULT_VEHTYPE" speedFactor="1.06" vaporized=""/>
    <tripinfo id="137" depart="475.00" departLane="E1_2_EB_0" departPos="5.10" departSpeed="0.00" departDelay="0.07" arrival="492.00" arrivalLane="E2_3_EB_0" arrivalPos="83.62" arrivalSpeed="13.81" duration="17.00" routeLength="185.72" waitingTime="0.00" waitingCount="0" stopTime="0.00" timeLoss="3.62" rerouteNo="0" devices="tripinfo_137 routing_137" vType="DEFAULT_VEHTYPE" speedFactor="1.00" vaporized=""/>
    <tripinfo id="122" depart="423.00" departLane="E1_2_EB_0" departPos="5.10" departSpeed="0.00" departDelay="0.07" arrival="494.00" arrivalLane="E3_6_SEB_0" arrivalPos="196.67" arrivalSpeed="5.00" duration="71.00" routeLength="485.47" waitingTime="13.00" waitingCount="3" stopTime="0.00" timeLoss="35.04" rerouteNo="1" devices="tripinfo_122 routing_122" vType="DEFAULT_VEHTYPE" speedFactor="1.02" vaporized=""/>
    <tripinfo id="125" depart="434.00" departLane="E3_6_SEB_0" departPos="5.10" departSpeed="0.00" departDelay="0.67" arrival="494.00" arrivalLane="E3_4_EB_0" arrivalPos="85.58" arrivalSpeed="12.96" duration="60.00" routeLength="292.60" waitingTime="30.00" waitingCount="1" stopTime="0.00" timeLoss="39.22" rerouteNo="0" devices="tripinfo_125 routing_125" vType="DEFAULT_VEHTYPE" speedFactor="1.03" vaporized=""/>
    <tripinfo id="102" depart="354.00" departLane="E3_6_NWB_0" departPos="5.10" departSpeed="0.00" departDelay="0.40" arrival="497.00" arrivalLane="E2_3_WB_0" arrivalPos="83.62" arrivalSpeed="12.27" duration="143.00" routeLength="838.40" waitingTime="38.00" waitingCount="3" stopTime="0.00" timeLoss="78.72" rerouteNo="1" devices="tripinfo_102 routing_102" vType="DEFAULT_VEHTYPE" speedFactor="0.97" vaporized=""/>
    <tripinfo id="76" depart="267.00" departLane="E2_6_SB_0" departPos="5.10" departSpeed="0.00" departDelay="3.53" arrival="500.00" arrivalLane="E2_6_NB_0" arrivalPos="175.06" arrivalSpeed="14.11" duration="233.00" routeLength="1311.76" waitingTime="87.00" waitingCount="5" stopTime="0.00" timeLoss="137.08" rerouteNo="1" devices="tripinfo_76 routing_76" vType="DEFAULT_VEHTYPE" speedFactor="1.03" vaporized=""/>
    <tripinfo id="141" depart="489.00" departLane="E6_7_SWB_0" departPos="5.10" departSpeed="0.00" departDelay="0.20" arrival="502.00" arrivalLane="E6_7_SWB_0" arrivalPos="125.94" arrivalSpeed="12.17" duration="13.00" routeLength="120.84" waitingTime="0.00" waitingCount="0" stopTime="0.00" timeLoss="3.09" rerouteNo="1" devices="tripinfo_141 routing_141" vType="DEFAULT_VEHTYPE" speedFactor="0.94" vaporized=""/>
    <tripinfo id="131" depart="455.00" departLane="E3_6_NWB_0" departPos="5.10" departSpeed="0.00" departDelay="0.87" arrival="503.00" arrivalLane="E2_3_EB_0" arrivalPos="83.62" arrivalSpeed="12.74" duration="48.00" routeLength="479.73" waitingTime="0.00" waitingCount="0" stopTime="0.00" timeLoss="9.78" rerouteNo="1" devices="tripinfo_131 routing_131" vType="DEFAULT_VEHTYPE" speedFactor="0.96" vaporized=""/>
    <tripinfo id="124" depart="430.00" departLane="E2_3_WB_0" departPos="5.10" departSpeed="0.00" departDelay="0.13" arrival="504.00" arrivalLane="E3_4_WB_0" arrivalPos="85.58" arrivalSpeed="13.85" duration="74.00" routeLength="812.74" waitingTime="0.00" waitingCount="0" stopTime="0.00" timeLoss="21.62" rerouteNo="1" devices="tripinfo_124 routing_124" vType="DEFAULT_VEHTYPE" speedFactor="1.15" vaporized=""/>
    <tripinfo id="87" depart="302.00" departLane="E2_3_EB_0" departPos="5.10" departSpeed="0.00" departDelay="0.40" arrival="506.00" arrivalLane="E2_6_NB_0" arrivalPos="175.06" arrivalSpeed="13.61" duration="204.00" routeLength="1122.51" waitingTime="66.00" waitingCount="4" stopTime="0.00" timeLoss="121.76" rerouteNo="1" devices="tripinfo_87 routing_87" vType="DEFAULT_VEHTYPE" speedFactor="1.04" vaporized=""/>
    <tripinfo id="140" depart="486.00" departLane="E2_6_SB_0" departPos="5.10" departSpeed="0.00" departDelay="0.67" arrival="509.00" arrivalLane="E2_3_EB_0" arrivalPos="83.62" arrivalSpeed="15.41" duration="23.00" routeLength="267.77" waitingTime="0.00" waitingCount="0" stopTime="0.00" timeLoss="5.83" rerouteNo="0" devices="tripinfo_140 routing_140" vType="DEFAULT_VEHTYPE" speedFactor="1.16" vaporized=""/>
    <tripinfo id="119" depart="413.00" departLane="E3_6_NWB_0" departPos="5.10" departSpeed="0.00" departDelay="0.47" arrival="512.00" arrivalLane="E4_7_NWB_0" arrivalPos="298.61" arrivalSpeed="12.09" duration="99.00" routeLength="894.67" waitingTime="5.00" waitingCount="1" stopTime="0.00" timeLoss="26.53" rerouteNo="1" devices="tripinfo_119 routing_119" vType="DEFAULT_VEHTYPE" speedFactor="0.94" vaporized=""/>
    <tripinfo id="138" depart="480.00" departLane="E2_6_SB_0" departPos="5.10" departSpeed="0.00" departDelay="1.60" arrival="515.00" arrivalLane="E3_4_EB_0" arrivalPos="85.58" arrivalSpeed="12.80" duration="35.00" routeLength="368.51" waitingTime="0.00" waitingCount="0" stopTime="0.00" timeLoss="5.87" rerouteNo="1" devices="tripinfo_138 routing_138" vType="DEFAULT_VEHTYPE" speedFactor="0.95" vaporized=""/>
    <tripinfo id="127" depart="465.00" departLane="E4_7_SEB_0" departPos="5.10" departSpeed="0.00" departDelay="24.73" arrival="517.00" arrivalLane="E3_6_NWB_0" arrivalPos="196.67" arrivalSpeed="14.27" duration="52.00" routeLength="596.77" waitingTime="0.00" waitingCount="0" stopTime="0.00" timeLoss="11.83" rerouteNo="1" devices="tripinfo_127 routing_127" vType="DEFAULT_VEHTYPE" speedFactor="1.12" vaporized=""/>
    <tripinfo id="146" depart="512.00" departLane="E2_3_WB_0" departPos="5.10" departSpeed="0.00" departDelay="5.87" arrival="521.00" arrivalLane="E2_3_WB_0" arrivalPos="83.62" arrivalSpeed="12.62" duration="9.00" routeLength="78.52" waitingTime="0.00" waitingCount="0" stopTime="0.00" timeLoss="3.20" rerouteNo="1" devices="tripinfo_146 routing_146" vType="DEFAULT_VEHTYPE" speedFactor="1.00" vaporized=""/>
    <tripinfo id="92" depart="321.00" departLane="E3_6_NWB_0" departPos="5.10" departSpeed="0.00" departDelay="2.07" arrival="525.00" arrivalLane="E6_7_SWB_0" arrivalPos="125.94" arrivalSpeed="10.31" duration="204.00" routeLength="1037.01" waitingTime="62.00" waitingCount="4" stopTime="0.00" timeLoss="109.08" rerouteNo="1" devices="tripinfo_92 routing_92" vType="DEFAULT_VEHTYPE" speedFactor="0.83" vaporized=""/>
    <tripinfo id="149" depart="517.00" departLane="E3_4_WB_0" departPos="5.10" departSpeed="0.00" departDelay="0.47" arrival="527.00" arrivalLane="E3_4_WB_0" arrivalPos="85.58" arrivalSpeed="13.23" duration="10.00" routeLength="80.48" waitingTime="0.00" waitingCount="0" stopTime="0.00" timeLoss="3.34" rerouteNo="1" devices="tripinfo_149 routing_149" vType="DEFAULT_VEHTYPE" speedFactor="0.96" vaporized=""/>
    <tripinfo id="136" depart="476.00" departLane="E6_7_SWB_0" departPos="5.10" departSpeed="0.00" departDelay="4.53" arrival="530.00" arrivalLane="E3_4_EB_0" arrivalPos="85.58" arrivalSpeed="13.94" duration="54.00" routeLength="442.09" waitingTime="10.00" waitingCount="1" stopTime="0.00" timeLoss="21.47" rerouteNo="1" devices="tripinfo_136 routing_136" vType="DEFAULT_VEHTYPE" speedFactor="1.02" vaporized=""/>
    <tripinfo id="134" depart="465.00" departLane="E4_7_NWB_0" departPos="5.10" departSpeed="0.00" departDelay="0.47" arrival="538.00" arrivalLane="E2_3_WB_0" arrivalPos="83.62" arrivalSpeed="13.05" duration="73.00" routeLength="748.87" waitingTime="0.00" waitingCount="0" stopTime="0.00" timeLoss="17.52" rerouteNo="1" devices="tripinfo_134 routing_134" vType="DEFAULT_VEHTYPE" speedFactor="1.01" vaporized=""/>
    <tripinfo id="106" depart="368.00" departLane="E6_7_NEB_0" departPos="5.10" departSpeed="0.00" departDelay="0.53" arrival="540.00" arrivalLane="E6_7_SWB_0" arrivalPos="125.94" arrivalSpeed="13.10" duration="172.00" routeLength="1572.27" waitingTime="27.00" waitingCount="2" stopTime="0.00" timeLoss="55.72" rerouteNo="1" devices="tripinfo_106 routing_106" vType="DEFAULT_VEHTYPE" speedFactor="1.03" vaporized=""/>
    <tripinfo id="129" depart="448.00" departLane="E2_3_EB_0" departPos="5.10" departSpeed="0.00" departDelay="0.80" arrival="541.00" arrivalLane="E2_3_WB_0" arrivalPos="83.62" arrivalSpeed="13.99" duration="93.00" routeLength="948.82" waitingTime="0.00" waitingCount="0" stopTime="0.00" timeLoss="23.32" rerouteNo="1" devices="tripinfo_129 routing_129" vType="DEFAULT_VEHTYPE" speedFactor="1.03" vaporized=""/>
    <tripinfo id="145" depart="503.00" departLane="E6_7_SWB_0" departPos="5.10" departSpeed="0.00" departDelay="0.33" arrival="545.00" arrivalLane="E2_3_EB_0" arrivalPos="83.62" arrivalSpeed="11.02" duration="42.00" routeLength="417.80" waitingTime="0.00" waitingCount="0" stopTime="0.00" timeLoss="6.48" rerouteNo="1" devices="tripinfo_145 routing_145" vType="DEFAULT_VEHTYPE" speedFactor="0.89" vaporized=""/>
    <tripinfo id="144" depart="500.00" departLane="E4_5_WB_0" departPos="5.10" departSpeed="0.00" departDelay="0.80" arrival="548.00" arrivalLane="E6_7_NEB_0" arrivalPos="125.94" arrivalSpeed="14.75" duration="48.00" routeLength="619.45" waitingTime="0.00" waitingCount="0" stopTime="0.00" timeLoss="8.01" rerouteNo="1" devices="tripinfo_144 routing_144" vType="DEFAULT_VEHTYPE" speedFactor="1.14" vaporized=""/>
    <tripinfo id="139" depart="482.00" departLane="E3_4_EB_0" departPos="5.10" departSpeed="0.00" departDelay="0.13" arrival="550.00" arrivalLane="E2_3_EB_0" arrivalPos="83.62" arrivalSpeed="14.57" duration="68.00" routeLength="833.98" waitingTime="0.00" waitingCount="0" stopTime="0.00" timeLoss="10.91" rerouteNo="1" devices="tripinfo_139 routing_139" vType="DEFAULT_VEHTYPE" speedFactor="1.11" vaporized=""/>
    <tripinfo id="126" depart="457.00" departLane="E4_7_SEB_0" departPos="5.10" departSpeed="0.00" departDelay="20.20" arrival="551.00" arrivalLane="E3_6_SEB_0" arrivalPos="196.67" arrivalSpeed="10.80" duration="94.00" routeLength="879.58" waitingTime="0.00" waitingCount="0" stopTime="0.00" timeLoss="13.06" rerouteNo="1" devices="tripinfo_126 routing_126" vType="DEFAULT_VEHTYPE" speedFactor="0.82" vaporized=""/>
    <tripinfo id="147" depart="510.00" departLane="E3_6_NWB_0" departPos="5.10" departSpeed="0.00" departDelay="0.40" arrival="554.00" arrivalLane="E7_8_NEB_0" arrivalPos="135.44" arrivalSpeed="12.83" duration="44.00" routeLength="487.75" waitingTime="0.00" waitingCount="0" stopTime="0.00" timeLoss="7.06" rerouteNo="1" devices="tripinfo_147 routing_147" vType="DEFAULT_VEHTYPE" speedFactor="0.97" vaporized=""/>
    <tripinfo id="150" depart="520.00" departLane="E2_6_SB_0" departPos="5.10" departSpeed="0.00" departDelay="0.00" arrival="554.00" arrivalLane="E3_4_EB_0" arrivalPos="85.58" arrivalSpeed="13.85" duration="34.00" routeLength="368.51" waitingTime="0.00" waitingCount="0" stopTime="0.00" timeLoss="6.81" rerouteNo="1" devices="tripinfo_150 routing_150" vType="DEFAULT_VEHTYPE" speedFactor="1.00" vaporized=""/>
    <tripinfo id="133" depart="462.00" departLane="E6_7_NEB_0" departPos="5.10" departSpeed="0.00" departDelay="0.93" arrival="555.00" arrivalLane="E3_6_SEB_0" arrivalPos="196.67" arrivalSpeed="10.16" duration="93.00" routeLength="1014.70" waitingTime="0.00" waitingCount="0" stopTime="0.00" timeLoss="30.51" rerouteNo="1" devices="tripinfo_133 routing_133" vType="DEFAULT_VEHTYPE" speedFactor="1.23" vaporized=""/>
    <tripinfo id="142" depart="493.00" departLane="E3_6_SEB_0" departPos="5.10" departSpeed="0.00" departDelay="0.73" arrival="556.00" arrivalLane="E6_7_NEB_0" arrivalPos="125.94" arrivalSpeed="15.20" duration="63.00" routeLength="616.12" waitingTime="8.00" waitingCount="1" stopTime="0.00" timeLoss="22.65" rerouteNo="1" devices="tripinfo_142 routing_142" vType="DEFAULT_VEHTYPE" speedFactor="1.13" vaporized=""/>
    <tripinfo id="120" depart="416.00" departLane="E3_4_EB_0" departPos="5.10" departSpeed="0.00" departDelay="0.00" arrival="585.00" arrivalLane="E3_4_WB_0" arrivalPos="85.58" arrivalSpeed="14.32" duration="169.00" routeLength="1584.26" waitingTime="26.00" waitingCount="3" stopTime="0.00" timeLoss="61.82" rerouteNo="1" devices="tripinfo_120 routing_120" vType="DEFAULT_VEHTYPE" speedFactor="1.10" vaporized=""/>
    <tripinfo id="148" depart="514.00" departLane="E3_6_NWB_0" departPos="5.10" departSpeed="0.00" departDelay="0.93" arrival="587.00" arrivalLane="E2_3_WB_0" arrivalPos="83.62" arrivalSpeed="14.08" duration="73.00" routeLength="838.40" waitingTime="0.00" waitingCount="0" stopTime="0.00" timeLoss="13.02" rerouteNo="1" devices="tripinfo_148 routing_148" vType="DEFAULT_VEHTYPE" speedFactor="1.04" vaporized=""/>
    <tripinfo id="132" depart="471.00" departLane="E4_7_SEB_0" departPos="5.10" departSpeed="0.00" departDelay="13.40" arrival="599.00" arrivalLane="E6_7_SWB_0" arrivalPos="125.94" arrivalSpeed="14.26" duration="128.00" routeLength="1437.15" waitingTime="0.00" waitingCount="0" stopTime="0.00" timeLoss="22.72" rerouteNo="1" devices="tripinfo_132 routing_132" vType="DEFAULT_VEHTYPE" speedFactor="1.04" vaporized=""/>
    <tripinfo id="143" depart="496.00" departLane="E3_6_SEB_0" departPos="5.10" departSpeed="0.00" departDelay="0.27" arrival="625.00" arrivalLane="E2_3_EB_0" arrivalPos="83.62" arrivalSpeed="9.65" duration="129.00" routeLength="1046.10" waitingTime="3.00" waitingCount="1" stopTime="0.00" timeLoss="22.12" rerouteNo="1" devices="tripinfo_143 routing_143" vType="DEFAULT_VEHTYPE" speedFactor="0.73" vaporized=""/>
</tripinfos>
